{"docs":{"0":{"id":0,"title":"Homepage","url":"/index.html","date":null,"categories":[]},"1":{"id":1,"title":"About me","url":"/intro.html","date":null,"categories":[]},"2":{"id":2,"title":"Projects","url":"/projects.html","date":null,"categories":[]},"3":{"id":3,"title":"Search Results","url":"/search.html","date":null,"categories":[]},"4":{"id":4,"title":"GAMEL - Game Script Using Scala DSL","url":"/2014/12/05/Scala-DSL-GAMEL","date":"2014-12-05 00:00:00 -0600","categories":[]},"5":{"id":5,"title":"Simple Ray Tracer","url":"/2015/03/04/Simple-Ray-Tracer","date":"2015-03-04 00:00:00 -0600","categories":[]}},"index":{"version":"0.4.5","fields":[{"name":"title","boost":10},{"name":"tags","boost":20},{"name":"body","boost":1}],"ref":"id","documentStore":{"store":{"0":["homepag"],"1":["2016","3.92","4.00","algebra","algorithm","architectur","artif","austin","b.","calculu","comput","cours","cs312)introduct","cs313k)logic","cs314)data","cs331h)introduct","cs343h)introduct","cs345h)program","cs347)oper","cs349)contemporari","cs384g)introduct","cs429h)comput","cs439h)oper","educ","equat","functions/discret","gpa","graduat","graphic","honor","integr","intellig","issu","languag","m341)linear","m358k)appli","m358k)number","m408c)differenti","m408d)sequenc","m427k)differenti","m427l)vector","math","mathemat","matrix","multivari","organ","program","progress","scholar","scienc","seri","set","statist","structur","summer","system","texa","theori","ture","univers"],"2":["2014","2015","4","5","dec","dsl","game","gamel","graphic","mar","project","rai","scala","script","simpl","tracer","us"],"3":["class=\"ty-post-timestamp","class=\"ty-post-titl","entri","href","li","pubdat","result","search","span","titl","url"],"4":["action","advantag","allow","argument","arrai","attribut","basic","call","condit","consist","contain","cooper","core","creat","default","defin","design","detail","develop","dsl","element","entiti","exampl","facilit","follow","foo","function","fundament","game","gamel","github","group","idea","inherit","instanc","intend","mansi","manual","mark","name","new","object","on","oop","overrid","paramet","player","project","propos","prototype/class","punch","scala","scene","script","similar","simpl","special","specif","specifi","syntax","take","thank","thing","trigger","type","under","us","user-defin"],"5":["adatp","antialias","antialis","artifact","attenu","basic","c","comput","cs384g","depth","distribut","featur","field","follow","glossi","graphic","implement","interpol","intersect","introduct","jitter","kd-tree","map","multithread","normal","optim","phong","polymesh","project","rai","reflect","refract","render","scene","shade","shadow","simpl","soft","trace","tracer","triangle/fac"]},"length":6},"tokenStore":{"root":{"2":{"0":{"1":{"4":{"docs":{"1":{"ref":1,"tf":0.05555555555555555},"2":{"ref":2,"tf":0.05555555555555555}}},"5":{"docs":{"1":{"ref":1,"tf":0.05555555555555555},"2":{"ref":2,"tf":0.05555555555555555}}},"6":{"docs":{"0":{"ref":0,"tf":0.012195121951219513},"1":{"ref":1,"tf":0.012345679012345678}}},"docs":{}},"docs":{}},"docs":{}},"3":{"docs":{},".":{"9":{"2":{"docs":{"0":{"ref":0,"tf":0.012195121951219513},"1":{"ref":1,"tf":0.012345679012345678}}},"docs":{}},"docs":{}}},"4":{"docs":{"1":{"ref":1,"tf":0.05555555555555555},"2":{"ref":2,"tf":0.05555555555555555}},".":{"0":{"0":{"docs":{"0":{"ref":0,"tf":0.012195121951219513},"1":{"ref":1,"tf":0.012345679012345678}}},"docs":{}},"docs":{}}},"5":{"docs":{"1":{"ref":1,"tf":0.05555555555555555},"2":{"ref":2,"tf":0.05555555555555555}}},"docs":{},"a":{"docs":{},"l":{"docs":{},"g":{"docs":{},"e":{"docs":{},"b":{"docs":{},"r":{"docs":{},"a":{"docs":{"0":{"ref":0,"tf":0.012195121951219513},"1":{"ref":1,"tf":0.012345679012345678}}}}}},"o":{"docs":{},"r":{"docs":{},"i":{"docs":{},"t":{"docs":{},"h":{"docs":{},"m":{"docs":{"0":{"ref":0,"tf":0.012195121951219513},"1":{"ref":1,"tf":0.012345679012345678}}}}}}}}},"l":{"docs":{},"o":{"docs":{},"w":{"docs":{"3":{"ref":3,"tf":0.006944444444444444},"4":{"ref":4,"tf":0.006944444444444444}}}}}},"r":{"docs":{},"c":{"docs":{},"h":{"docs":{},"i":{"docs":{},"t":{"docs":{},"e":{"docs":{},"c":{"docs":{},"t":{"docs":{},"u":{"docs":{},"r":{"docs":{"0":{"ref":0,"tf":0.012195121951219513},"1":{"ref":1,"tf":0.012345679012345678}}}}}}}}}}},"t":{"docs":{},"i":{"docs":{},"f":{"docs":{"0":{"ref":0,"tf":0.012195121951219513},"1":{"ref":1,"tf":0.012345679012345678}},"a":{"docs":{},"c":{"docs":{},"t":{"docs":{"4":{"ref":4,"tf":0.01818181818181818},"5":{"ref":5,"tf":0.01818181818181818}}}}}},"c":{"docs":{},"l":{"docs":{"2":{"ref":2,"tf":0.125}}}}}},"g":{"docs":{},"u":{"docs":{},"m":{"docs":{},"e":{"docs":{},"n":{"docs":{},"t":{"docs":{"3":{"ref":3,"tf":0.006944444444444444},"4":{"ref":4,"tf":0.006944444444444444}}}}}}}},"r":{"docs":{},"a":{"docs":{},"i":{"docs":{"3":{"ref":3,"tf":0.006944444444444444},"4":{"ref":4,"tf":0.006944444444444444}}}}}},"u":{"docs":{},"s":{"docs":{},"t":{"docs":{},"i":{"docs":{},"n":{"docs":{"0":{"ref":0,"tf":0.012195121951219513},"1":{"ref":1,"tf":0.012345679012345678}}}}}}},"c":{"docs":{},"t":{"docs":{},"i":{"docs":{},"o":{"docs":{},"n":{"docs":{"3":{"ref":3,"tf":0.0763888888888889},"4":{"ref":4,"tf":0.0763888888888889}}}}}}},"d":{"docs":{},"v":{"docs":{},"a":{"docs":{},"n":{"docs":{},"t":{"docs":{},"a":{"docs":{},"g":{"docs":{"3":{"ref":3,"tf":0.006944444444444444},"4":{"ref":4,"tf":0.006944444444444444}}}}}}}},"a":{"docs":{},"t":{"docs":{},"p":{"docs":{"4":{"ref":4,"tf":0.01818181818181818},"5":{"ref":5,"tf":0.01818181818181818}}}}}},"t":{"docs":{},"t":{"docs":{},"r":{"docs":{},"i":{"docs":{},"b":{"docs":{},"u":{"docs":{},"t":{"docs":{"3":{"ref":3,"tf":0.020833333333333332},"4":{"ref":4,"tf":0.020833333333333332}}}}}}},"e":{"docs":{},"n":{"docs":{},"u":{"docs":{"4":{"ref":4,"tf":0.01818181818181818},"5":{"ref":5,"tf":0.01818181818181818}}}}}}},"n":{"docs":{},"t":{"docs":{},"i":{"docs":{},"a":{"docs":{},"l":{"docs":{},"i":{"docs":{},"a":{"docs":{},"s":{"docs":{"4":{"ref":4,"tf":0.03636363636363636},"5":{"ref":5,"tf":0.03636363636363636}}}},"s":{"docs":{"4":{"ref":4,"tf":0.01818181818181818},"5":{"ref":5,"tf":0.01818181818181818}}}}}}}}}},"b":{"docs":{"2":{"ref":2,"tf":0.03125}},".":{"docs":{"0":{"ref":0,"tf":0.024390243902439025},"1":{"ref":1,"tf":0.024691358024691357}}},"a":{"docs":{},"s":{"docs":{},"i":{"docs":{},"c":{"docs":{"3":{"ref":3,"tf":0.006944444444444444},"4":{"ref":4,"tf":0.006944444444444444},"5":{"ref":5,"tf":0.01818181818181818}}}}}}},"c":{"docs":{"4":{"ref":4,"tf":0.01818181818181818},"5":{"ref":5,"tf":0.01818181818181818}},"a":{"docs":{},"l":{"docs":{},"c":{"docs":{},"u":{"docs":{},"l":{"docs":{},"u":{"docs":{"0":{"ref":0,"tf":0.036585365853658534},"1":{"ref":1,"tf":0.037037037037037035}}}}}},"l":{"docs":{"3":{"ref":3,"tf":0.020833333333333332},"4":{"ref":4,"tf":0.020833333333333332}}}}},"o":{"docs":{},"m":{"docs":{},"p":{"docs":{},"u":{"docs":{},"t":{"docs":{"0":{"ref":0,"tf":0.04878048780487805},"1":{"ref":1,"tf":0.04938271604938271},"4":{"ref":4,"tf":0.01818181818181818},"5":{"ref":5,"tf":0.01818181818181818}}}}}},"u":{"docs":{},"r":{"docs":{},"s":{"docs":{"0":{"ref":0,"tf":0.024390243902439025},"1":{"ref":1,"tf":0.024691358024691357}}}}},"n":{"docs":{},"d":{"docs":{},"i":{"docs":{},"t":{"docs":{"3":{"ref":3,"tf":0.006944444444444444},"4":{"ref":4,"tf":0.006944444444444444}}}}},"s":{"docs":{},"i":{"docs":{},"s":{"docs":{},"t":{"docs":{"3":{"ref":3,"tf":0.006944444444444444},"4":{"ref":4,"tf":0.006944444444444444}}}}}},"t":{"docs":{},"a":{"docs":{},"i":{"docs":{},"n":{"docs":{"3":{"ref":3,"tf":0.006944444444444444},"4":{"ref":4,"tf":0.006944444444444444}}}}}}},"o":{"docs":{},"p":{"docs":{},"e":{"docs":{},"r":{"docs":{"3":{"ref":3,"tf":0.006944444444444444},"4":{"ref":4,"tf":0.006944444444444444}}}}}},"r":{"docs":{},"e":{"docs":{"3":{"ref":3,"tf":0.006944444444444444},"4":{"ref":4,"tf":0.006944444444444444}}}}},"s":{"3":{"1":{"2":{"docs":{},")":{"docs":{},"i":{"docs":{},"n":{"docs":{},"t":{"docs":{},"r":{"docs":{},"o":{"docs":{},"d":{"docs":{},"u":{"docs":{},"c":{"docs":{},"t":{"docs":{"0":{"ref":0,"tf":0.012195121951219513},"1":{"ref":1,"tf":0.012345679012345678}}}}}}}}}}}}},"3":{"docs":{},"k":{"docs":{},")":{"docs":{},"l":{"docs":{},"o":{"docs":{},"g":{"docs":{},"i":{"docs":{},"c":{"docs":{"0":{"ref":0,"tf":0.012195121951219513},"1":{"ref":1,"tf":0.012345679012345678}}}}}}}}}},"4":{"docs":{},")":{"docs":{},"d":{"docs":{},"a":{"docs":{},"t":{"docs":{},"a":{"docs":{"0":{"ref":0,"tf":0.012195121951219513},"1":{"ref":1,"tf":0.012345679012345678}}}}}}}},"docs":{}},"3":{"1":{"docs":{},"h":{"docs":{},")":{"docs":{},"i":{"docs":{},"n":{"docs":{},"t":{"docs":{},"r":{"docs":{},"o":{"docs":{},"d":{"docs":{},"u":{"docs":{},"c":{"docs":{},"t":{"docs":{"0":{"ref":0,"tf":0.012195121951219513},"1":{"ref":1,"tf":0.012345679012345678}}}}}}}}}}}}}},"docs":{}},"4":{"3":{"docs":{},"h":{"docs":{},")":{"docs":{},"i":{"docs":{},"n":{"docs":{},"t":{"docs":{},"r":{"docs":{},"o":{"docs":{},"d":{"docs":{},"u":{"docs":{},"c":{"docs":{},"t":{"docs":{"0":{"ref":0,"tf":0.012195121951219513},"1":{"ref":1,"tf":0.012345679012345678}}}}}}}}}}}}}},"5":{"docs":{},"h":{"docs":{},")":{"docs":{},"p":{"docs":{},"r":{"docs":{},"o":{"docs":{},"g":{"docs":{},"r":{"docs":{},"a":{"docs":{},"m":{"docs":{"0":{"ref":0,"tf":0.012195121951219513},"1":{"ref":1,"tf":0.012345679012345678}}}}}}}}}}}},"7":{"docs":{},")":{"docs":{},"o":{"docs":{},"p":{"docs":{},"e":{"docs":{},"r":{"docs":{"0":{"ref":0,"tf":0.012195121951219513},"1":{"ref":1,"tf":0.012345679012345678}}}}}}}},"9":{"docs":{},")":{"docs":{},"c":{"docs":{},"o":{"docs":{},"n":{"docs":{},"t":{"docs":{},"e":{"docs":{},"m":{"docs":{},"p":{"docs":{},"o":{"docs":{},"r":{"docs":{},"a":{"docs":{},"r":{"docs":{},"i":{"docs":{"0":{"ref":0,"tf":0.012195121951219513},"1":{"ref":1,"tf":0.012345679012345678}}}}}}}}}}}}}}}},"docs":{}},"8":{"4":{"docs":{},"g":{"docs":{"4":{"ref":4,"tf":0.01818181818181818},"5":{"ref":5,"tf":0.01818181818181818}},")":{"docs":{},"i":{"docs":{},"n":{"docs":{},"t":{"docs":{},"r":{"docs":{},"o":{"docs":{},"d":{"docs":{},"u":{"docs":{},"c":{"docs":{},"t":{"docs":{"0":{"ref":0,"tf":0.012195121951219513},"1":{"ref":1,"tf":0.012345679012345678}}}}}}}}}}}}}},"docs":{}},"docs":{}},"4":{"2":{"9":{"docs":{},"h":{"docs":{},")":{"docs":{},"c":{"docs":{},"o":{"docs":{},"m":{"docs":{},"p":{"docs":{},"u":{"docs":{},"t":{"docs":{"0":{"ref":0,"tf":0.012195121951219513},"1":{"ref":1,"tf":0.012345679012345678}}}}}}}}}}},"docs":{}},"3":{"9":{"docs":{},"h":{"docs":{},")":{"docs":{},"o":{"docs":{},"p":{"docs":{},"e":{"docs":{},"r":{"docs":{"0":{"ref":0,"tf":0.012195121951219513},"1":{"ref":1,"tf":0.012345679012345678}}}}}}}}},"docs":{}},"docs":{}},"docs":{}},"l":{"docs":{},"a":{"docs":{},"s":{"docs":{},"s":{"docs":{},"=":{"docs":{},"\"":{"docs":{},"t":{"docs":{},"y":{"docs":{},"-":{"docs":{},"p":{"docs":{},"o":{"docs":{},"s":{"docs":{},"t":{"docs":{},"-":{"docs":{},"t":{"docs":{},"i":{"docs":{},"m":{"docs":{},"e":{"docs":{},"s":{"docs":{},"t":{"docs":{},"a":{"docs":{},"m":{"docs":{},"p":{"docs":{"2":{"ref":2,"tf":0.07142857142857142},"3":{"ref":3,"tf":0.07142857142857142}}}}}}}}},"t":{"docs":{},"l":{"docs":{"2":{"ref":2,"tf":0.07142857142857142},"3":{"ref":3,"tf":0.07142857142857142}}}}}}}}}}}}}},"r":{"docs":{},"e":{"docs":{},"l":{"docs":{"2":{"ref":2,"tf":0.045454545454545456}}}}}}}}}}},"r":{"docs":{},"e":{"docs":{},"a":{"docs":{},"t":{"docs":{"3":{"ref":3,"tf":0.041666666666666664},"4":{"ref":4,"tf":0.041666666666666664}}}}}}},"e":{"docs":{"2":{"ref":2,"tf":0.03125}},"d":{"docs":{},"u":{"docs":{},"c":{"docs":{"0":{"ref":0,"tf":0.012195121951219513},"1":{"ref":1,"tf":0.012345679012345678}}}}},"q":{"docs":{},"u":{"docs":{},"a":{"docs":{},"t":{"docs":{"0":{"ref":0,"tf":0.012195121951219513},"1":{"ref":1,"tf":0.012345679012345678}}}}}},"n":{"docs":{},"t":{"docs":{},"r":{"docs":{},"i":{"docs":{"2":{"ref":2,"tf":0.14285714285714285},"3":{"ref":3,"tf":0.14285714285714285}}}},"i":{"docs":{},"t":{"docs":{},"i":{"docs":{"3":{"ref":3,"tf":0.04861111111111111},"4":{"ref":4,"tf":0.04861111111111111}}}}}},"d":{"docs":{},"f":{"docs":{},"o":{"docs":{},"r":{"docs":{"2":{"ref":2,"tf":0.038461538461538464}}}}}}},"l":{"docs":{},"e":{"docs":{},"m":{"docs":{},"e":{"docs":{},"n":{"docs":{},"t":{"docs":{"3":{"ref":3,"tf":0.006944444444444444},"4":{"ref":4,"tf":0.006944444444444444}}}}}}}},"x":{"docs":{},"a":{"docs":{},"m":{"docs":{},"p":{"docs":{},"l":{"docs":{"3":{"ref":3,"tf":0.006944444444444444},"4":{"ref":4,"tf":0.006944444444444444}}}}}}}},"f":{"docs":{},"u":{"docs":{},"n":{"docs":{},"c":{"docs":{},"t":{"docs":{},"i":{"docs":{},"o":{"docs":{},"n":{"docs":{"3":{"ref":3,"tf":0.013888888888888888},"4":{"ref":4,"tf":0.013888888888888888}},"s":{"docs":{},"/":{"docs":{},"d":{"docs":{},"i":{"docs":{},"s":{"docs":{},"c":{"docs":{},"r":{"docs":{},"e":{"docs":{},"t":{"docs":{"0":{"ref":0,"tf":0.012195121951219513},"1":{"ref":1,"tf":0.012345679012345678}}}}}}}}}}}}}}}},"d":{"docs":{},"a":{"docs":{},"m":{"docs":{},"e":{"docs":{},"n":{"docs":{},"t":{"docs":{"3":{"ref":3,"tf":0.006944444444444444},"4":{"ref":4,"tf":0.006944444444444444}}}}}}}}}},"a":{"docs":{},"c":{"docs":{},"i":{"docs":{},"l":{"docs":{},"i":{"docs":{},"t":{"docs":{"3":{"ref":3,"tf":0.006944444444444444},"4":{"ref":4,"tf":0.006944444444444444}}}}}}}},"o":{"docs":{},"l":{"docs":{},"l":{"docs":{},"o":{"docs":{},"w":{"docs":{"3":{"ref":3,"tf":0.027777777777777776},"4":{"ref":4,"tf":0.027777777777777776},"5":{"ref":5,"tf":0.03636363636363636}}}}}},"o":{"docs":{"3":{"ref":3,"tf":0.08333333333333333},"4":{"ref":4,"tf":0.08333333333333333}}}},"e":{"docs":{},"a":{"docs":{},"t":{"docs":{},"u":{"docs":{},"r":{"docs":{"4":{"ref":4,"tf":0.01818181818181818},"5":{"ref":5,"tf":0.01818181818181818}}}}}}},"i":{"docs":{},"e":{"docs":{},"l":{"docs":{},"d":{"docs":{"4":{"ref":4,"tf":0.01818181818181818},"5":{"ref":5,"tf":0.01818181818181818}}}}}}},"g":{"docs":{},"p":{"docs":{},"a":{"docs":{"0":{"ref":0,"tf":0.024390243902439025},"1":{"ref":1,"tf":0.024691358024691357}}}},"r":{"docs":{},"a":{"docs":{},"d":{"docs":{},"u":{"docs":{},"a":{"docs":{},"t":{"docs":{"0":{"ref":0,"tf":0.012195121951219513},"1":{"ref":1,"tf":0.012345679012345678}}}}}},"p":{"docs":{},"h":{"docs":{},"i":{"docs":{},"c":{"docs":{"0":{"ref":0,"tf":0.012195121951219513},"1":{"ref":1,"tf":0.012345679012345678},"2":{"ref":2,"tf":0.05555555555555555},"4":{"ref":4,"tf":0.01818181818181818},"5":{"ref":5,"tf":0.01818181818181818}}}}}}},"o":{"docs":{},"u":{"docs":{},"p":{"docs":{"3":{"ref":3,"tf":0.006944444444444444},"4":{"ref":4,"tf":0.006944444444444444}}}}}},"a":{"docs":{},"m":{"docs":{},"e":{"docs":{"1":{"ref":1,"tf":0.05555555555555555},"2":{"ref":2,"tf":0.05555555555555555},"3":{"ref":3,"tf":1.6874999999999998},"4":{"ref":4,"tf":1.6874999999999998}},"l":{"docs":{"1":{"ref":1,"tf":0.05555555555555555},"2":{"ref":2,"tf":0.05555555555555555},"3":{"ref":3,"tf":1.673611111111111},"4":{"ref":4,"tf":1.673611111111111}}}}}},"i":{"docs":{},"t":{"docs":{},"h":{"docs":{},"u":{"docs":{},"b":{"docs":{"3":{"ref":3,"tf":0.006944444444444444},"4":{"ref":4,"tf":0.006944444444444444}}}}}}},"l":{"docs":{},"o":{"docs":{},"s":{"docs":{},"s":{"docs":{},"i":{"docs":{"4":{"ref":4,"tf":0.01818181818181818},"5":{"ref":5,"tf":0.01818181818181818}}}}}}}},"h":{"3":{"docs":{"2":{"ref":2,"tf":0.125}}},"docs":{},"o":{"docs":{},"m":{"docs":{},"e":{"docs":{},"p":{"docs":{},"a":{"docs":{},"g":{"docs":{"0":{"ref":0,"tf":10},"1":{"ref":1,"tf":10},"2":{"ref":2,"tf":10}}}}}}},"n":{"docs":{},"o":{"docs":{},"r":{"docs":{"0":{"ref":0,"tf":0.07317073170731707},"1":{"ref":1,"tf":0.07407407407407407}}}}}},"r":{"docs":{},"e":{"docs":{},"f":{"docs":{"2":{"ref":2,"tf":0.07142857142857142},"3":{"ref":3,"tf":0.07142857142857142}},"=":{"docs":{},"\"":{"docs":{},"{":{"docs":{},"{":{"docs":{},"u":{"docs":{},"r":{"docs":{},"l":{"docs":{},"}":{"docs":{},"}":{"docs":{},"\"":{"docs":{},">":{"docs":{},"{":{"docs":{},"{":{"docs":{},"t":{"docs":{},"i":{"docs":{},"t":{"docs":{},"l":{"docs":{},"e":{"docs":{},"}":{"docs":{},"}":{"docs":{},"<":{"docs":{},"/":{"docs":{},"a":{"docs":{"2":{"ref":2,"tf":0.0625}}}}}}}}}}}}}}}}}}}}}}}}}}}}},"i":{"docs":{},"n":{"docs":{},"t":{"docs":{},"e":{"docs":{},"g":{"docs":{},"r":{"docs":{"0":{"ref":0,"tf":0.012195121951219513},"1":{"ref":1,"tf":0.012345679012345678}}}},"l":{"docs":{},"l":{"docs":{},"i":{"docs":{},"g":{"docs":{"0":{"ref":0,"tf":0.012195121951219513},"1":{"ref":1,"tf":0.012345679012345678}}}}}},"n":{"docs":{},"d":{"docs":{"3":{"ref":3,"tf":0.006944444444444444},"4":{"ref":4,"tf":0.006944444444444444}}}},"r":{"docs":{},"p":{"docs":{},"o":{"docs":{},"l":{"docs":{"4":{"ref":4,"tf":0.01818181818181818},"5":{"ref":5,"tf":0.01818181818181818}}}}},"s":{"docs":{},"e":{"docs":{},"c":{"docs":{},"t":{"docs":{"4":{"ref":4,"tf":0.01818181818181818},"5":{"ref":5,"tf":0.01818181818181818}}}}}}}},"r":{"docs":{},"o":{"docs":{},"d":{"docs":{},"u":{"docs":{},"c":{"docs":{},"t":{"docs":{"0":{"ref":0,"tf":0.012195121951219513},"1":{"ref":1,"tf":0.012195121951219513},"4":{"ref":4,"tf":0.01818181818181818},"5":{"ref":5,"tf":0.01818181818181818}}}}}}}}},"h":{"docs":{},"e":{"docs":{},"r":{"docs":{},"i":{"docs":{},"t":{"docs":{"3":{"ref":3,"tf":0.006944444444444444},"4":{"ref":4,"tf":0.006944444444444444}}}}}}},"s":{"docs":{},"t":{"docs":{},"a":{"docs":{},"n":{"docs":{},"c":{"docs":{"3":{"ref":3,"tf":0.0763888888888889},"4":{"ref":4,"tf":0.0763888888888889}}}}}}}},"s":{"docs":{},"s":{"docs":{},"u":{"docs":{"0":{"ref":0,"tf":0.012195121951219513},"1":{"ref":1,"tf":0.012345679012345678}}}}},"d":{"docs":{},"e":{"docs":{},"a":{"docs":{"3":{"ref":3,"tf":0.006944444444444444},"4":{"ref":4,"tf":0.006944444444444444}}}}},"m":{"docs":{},"p":{"docs":{},"l":{"docs":{},"e":{"docs":{},"m":{"docs":{},"e":{"docs":{},"n":{"docs":{},"t":{"docs":{"4":{"ref":4,"tf":0.01818181818181818},"5":{"ref":5,"tf":0.01818181818181818}}}}}}}}}}},"l":{"docs":{},"a":{"docs":{},"n":{"docs":{},"g":{"docs":{},"u":{"docs":{},"a":{"docs":{},"g":{"docs":{"0":{"ref":0,"tf":0.012195121951219513},"1":{"ref":1,"tf":0.012345679012345678}}}}}}}},"i":{"docs":{"2":{"ref":2,"tf":0.14285714285714285},"3":{"ref":3,"tf":0.14285714285714285}}}},"m":{"3":{"4":{"1":{"docs":{},")":{"docs":{},"l":{"docs":{},"i":{"docs":{},"n":{"docs":{},"e":{"docs":{},"a":{"docs":{},"r":{"docs":{"0":{"ref":0,"tf":0.012195121951219513},"1":{"ref":1,"tf":0.012345679012345678}}}}}}}}}},"docs":{}},"5":{"8":{"docs":{},"k":{"docs":{},")":{"docs":{},"a":{"docs":{},"p":{"docs":{},"p":{"docs":{},"l":{"docs":{},"i":{"docs":{"0":{"ref":0,"tf":0.012195121951219513},"1":{"ref":1,"tf":0.012345679012345678}}}}}}},"n":{"docs":{},"u":{"docs":{},"m":{"docs":{},"b":{"docs":{},"e":{"docs":{},"r":{"docs":{"0":{"ref":0,"tf":0.012195121951219513},"1":{"ref":1,"tf":0.012345679012345678}}}}}}}}}}},"docs":{}},"docs":{}},"4":{"0":{"8":{"docs":{},"c":{"docs":{},")":{"docs":{},"d":{"docs":{},"i":{"docs":{},"f":{"docs":{},"f":{"docs":{},"e":{"docs":{},"r":{"docs":{},"e":{"docs":{},"n":{"docs":{},"t":{"docs":{},"i":{"docs":{"0":{"ref":0,"tf":0.012195121951219513},"1":{"ref":1,"tf":0.012345679012345678}}}}}}}}}}}}}},"d":{"docs":{},")":{"docs":{},"s":{"docs":{},"e":{"docs":{},"q":{"docs":{},"u":{"docs":{},"e":{"docs":{},"n":{"docs":{},"c":{"docs":{"0":{"ref":0,"tf":0.012195121951219513},"1":{"ref":1,"tf":0.012345679012345678}}}}}}}}}}}},"docs":{}},"2":{"7":{"docs":{},"k":{"docs":{},")":{"docs":{},"d":{"docs":{},"i":{"docs":{},"f":{"docs":{},"f":{"docs":{},"e":{"docs":{},"r":{"docs":{},"e":{"docs":{},"n":{"docs":{},"t":{"docs":{},"i":{"docs":{"0":{"ref":0,"tf":0.012195121951219513},"1":{"ref":1,"tf":0.012345679012345678}}}}}}}}}}}}}},"l":{"docs":{},")":{"docs":{},"v":{"docs":{},"e":{"docs":{},"c":{"docs":{},"t":{"docs":{},"o":{"docs":{},"r":{"docs":{"0":{"ref":0,"tf":0.012195121951219513},"1":{"ref":1,"tf":0.012345679012345678}}}}}}}}}}},"docs":{}},"docs":{}},"docs":{},"a":{"docs":{},"t":{"docs":{},"h":{"docs":{"0":{"ref":0,"tf":0.012195121951219513},"1":{"ref":1,"tf":0.012345679012345678}},"e":{"docs":{},"m":{"docs":{},"a":{"docs":{},"t":{"docs":{"0":{"ref":0,"tf":0.024390243902439025},"1":{"ref":1,"tf":0.024691358024691357}}}}}}},"r":{"docs":{},"i":{"docs":{},"x":{"docs":{"0":{"ref":0,"tf":0.012195121951219513},"1":{"ref":1,"tf":0.012345679012345678}}}}}},"r":{"docs":{"1":{"ref":1,"tf":0.05555555555555555},"2":{"ref":2,"tf":0.05555555555555555}},"k":{"docs":{"3":{"ref":3,"tf":0.006944444444444444},"4":{"ref":4,"tf":0.006944444444444444}}}},"n":{"docs":{},"s":{"docs":{},"i":{"docs":{"3":{"ref":3,"tf":0.006944444444444444},"4":{"ref":4,"tf":0.006944444444444444}}}},"u":{"docs":{},"a":{"docs":{},"l":{"docs":{"3":{"ref":3,"tf":0.006944444444444444},"4":{"ref":4,"tf":0.006944444444444444}}}}}},"p":{"docs":{"4":{"ref":4,"tf":0.01818181818181818},"5":{"ref":5,"tf":0.01818181818181818}}}},"u":{"docs":{},"l":{"docs":{},"t":{"docs":{},"i":{"docs":{},"v":{"docs":{},"a":{"docs":{},"r":{"docs":{},"i":{"docs":{"0":{"ref":0,"tf":0.012195121951219513},"1":{"ref":1,"tf":0.012345679012345678}}}}}},"t":{"docs":{},"h":{"docs":{},"r":{"docs":{},"e":{"docs":{},"a":{"docs":{},"d":{"docs":{"4":{"ref":4,"tf":0.01818181818181818},"5":{"ref":5,"tf":0.01818181818181818}}}}}}}}}}}}},"o":{"docs":{},"r":{"docs":{},"g":{"docs":{},"a":{"docs":{},"n":{"docs":{"0":{"ref":0,"tf":0.012195121951219513},"1":{"ref":1,"tf":0.012345679012345678}}}}}},"b":{"docs":{},"j":{"docs":{},"e":{"docs":{},"c":{"docs":{},"t":{"docs":{"3":{"ref":3,"tf":0.013888888888888888},"4":{"ref":4,"tf":0.013888888888888888}}}}}}},"n":{"docs":{"3":{"ref":3,"tf":0.020833333333333332},"4":{"ref":4,"tf":0.020833333333333332}}},"o":{"docs":{},"p":{"docs":{"3":{"ref":3,"tf":0.006944444444444444},"4":{"ref":4,"tf":0.006944444444444444}}}},"v":{"docs":{},"e":{"docs":{},"r":{"docs":{},"r":{"docs":{},"i":{"docs":{},"d":{"docs":{"3":{"ref":3,"tf":0.006944444444444444},"4":{"ref":4,"tf":0.006944444444444444}}}}}}}},"p":{"docs":{},"t":{"docs":{},"i":{"docs":{},"m":{"docs":{"4":{"ref":4,"tf":0.01818181818181818},"5":{"ref":5,"tf":0.01818181818181818}}}}}}},"p":{"docs":{},"r":{"docs":{},"o":{"docs":{},"g":{"docs":{},"r":{"docs":{},"a":{"docs":{},"m":{"docs":{"0":{"ref":0,"tf":0.012195121951219513},"1":{"ref":1,"tf":0.012345679012345678}}}},"e":{"docs":{},"s":{"docs":{},"s":{"docs":{"0":{"ref":0,"tf":0.04878048780487805},"1":{"ref":1,"tf":0.04938271604938271}}}}}}},"j":{"docs":{},"e":{"docs":{},"c":{"docs":{},"t":{"docs":{"1":{"ref":1,"tf":10},"2":{"ref":2,"tf":10},"3":{"ref":3,"tf":0.013888888888888888},"4":{"ref":4,"tf":0.013888888888888888},"5":{"ref":5,"tf":0.03636363636363636}}}}}},"p":{"docs":{},"o":{"docs":{},"s":{"docs":{"3":{"ref":3,"tf":0.006944444444444444},"4":{"ref":4,"tf":0.006944444444444444}}}}},"t":{"docs":{},"o":{"docs":{},"t":{"docs":{},"y":{"docs":{},"p":{"docs":{},"e":{"docs":{},"/":{"docs":{},"c":{"docs":{},"l":{"docs":{},"a":{"docs":{},"s":{"docs":{},"s":{"docs":{"3":{"ref":3,"tf":0.006944444444444444},"4":{"ref":4,"tf":0.006944444444444444}}}}}}}}}}}}}}}},"u":{"docs":{},"b":{"docs":{},"d":{"docs":{},"a":{"docs":{},"t":{"docs":{"2":{"ref":2,"tf":0.07142857142857142},"3":{"ref":3,"tf":0.07142857142857142}},"e":{"docs":{},">":{"docs":{},"{":{"docs":{},"{":{"docs":{},"d":{"docs":{},"i":{"docs":{},"s":{"docs":{},"p":{"docs":{},"l":{"docs":{},"a":{"docs":{},"y":{"docs":{},"d":{"docs":{},"a":{"docs":{},"t":{"docs":{},"e":{"docs":{},"}":{"docs":{},"}":{"docs":{},"<":{"docs":{},"/":{"docs":{},"t":{"docs":{},"i":{"docs":{},"m":{"docs":{"2":{"ref":2,"tf":0.0625}}}}}}}}}}}}}}}}}}}}}}}}}}}},"n":{"docs":{},"c":{"docs":{},"h":{"docs":{"3":{"ref":3,"tf":0.006944444444444444},"4":{"ref":4,"tf":0.006944444444444444}}}}}},"a":{"docs":{},"r":{"docs":{},"a":{"docs":{},"m":{"docs":{},"e":{"docs":{},"t":{"docs":{"3":{"ref":3,"tf":0.006944444444444444},"4":{"ref":4,"tf":0.006944444444444444}}}}}}}},"l":{"docs":{},"a":{"docs":{},"y":{"docs":{},"e":{"docs":{},"r":{"docs":{"3":{"ref":3,"tf":0.006944444444444444},"4":{"ref":4,"tf":0.006944444444444444}}}}}}},"h":{"docs":{},"o":{"docs":{},"n":{"docs":{},"g":{"docs":{"4":{"ref":4,"tf":0.01818181818181818},"5":{"ref":5,"tf":0.01818181818181818}}}}}},"o":{"docs":{},"l":{"docs":{},"y":{"docs":{},"m":{"docs":{},"e":{"docs":{},"s":{"docs":{},"h":{"docs":{"4":{"ref":4,"tf":0.01818181818181818},"5":{"ref":5,"tf":0.01818181818181818}}}}}}}},"s":{"docs":{},"t":{"docs":{"2":{"ref":2,"tf":0.038461538461538464}},".":{"docs":{},"u":{"docs":{},"r":{"docs":{},"l":{"docs":{"2":{"ref":2,"tf":0.07142857142857142}}}}}}}}}},"s":{"docs":{},"c":{"docs":{},"h":{"docs":{},"o":{"docs":{},"l":{"docs":{},"a":{"docs":{},"r":{"docs":{"0":{"ref":0,"tf":0.012195121951219513},"1":{"ref":1,"tf":0.012345679012345678}}}}}}},"i":{"docs":{},"e":{"docs":{},"n":{"docs":{},"c":{"docs":{"0":{"ref":0,"tf":0.036585365853658534},"1":{"ref":1,"tf":0.037037037037037035}}}}}},"a":{"docs":{},"l":{"docs":{},"a":{"docs":{"1":{"ref":1,"tf":0.1111111111111111},"2":{"ref":2,"tf":0.1111111111111111},"3":{"ref":3,"tf":1.6805555555555554},"4":{"ref":4,"tf":1.6805555555555554}}}}},"r":{"docs":{},"i":{"docs":{},"p":{"docs":{},"t":{"docs":{"1":{"ref":1,"tf":0.05555555555555555},"2":{"ref":2,"tf":0.05555555555555555},"3":{"ref":3,"tf":1.673611111111111},"4":{"ref":4,"tf":1.673611111111111}}}}}},"e":{"docs":{},"n":{"docs":{},"e":{"docs":{"3":{"ref":3,"tf":0.013888888888888888},"4":{"ref":4,"tf":0.013888888888888888},"5":{"ref":5,"tf":0.01818181818181818}}}}}},"e":{"docs":{},"r":{"docs":{},"i":{"docs":{"0":{"ref":0,"tf":0.012195121951219513},"1":{"ref":1,"tf":0.012345679012345678}}}},"t":{"docs":{"0":{"ref":0,"tf":0.012195121951219513},"1":{"ref":1,"tf":0.012345679012345678}}},"a":{"docs":{},"r":{"docs":{},"c":{"docs":{},"h":{"docs":{"2":{"ref":2,"tf":5.071428571428571},"3":{"ref":3,"tf":5.071428571428571}}}}}}},"t":{"docs":{},"a":{"docs":{},"t":{"docs":{},"i":{"docs":{},"s":{"docs":{},"t":{"docs":{"0":{"ref":0,"tf":0.012195121951219513},"1":{"ref":1,"tf":0.012345679012345678}}}}}}},"r":{"docs":{},"u":{"docs":{},"c":{"docs":{},"t":{"docs":{},"u":{"docs":{},"r":{"docs":{"0":{"ref":0,"tf":0.012195121951219513},"1":{"ref":1,"tf":0.012345679012345678}}}}}}}}},"u":{"docs":{},"m":{"docs":{},"m":{"docs":{},"e":{"docs":{},"r":{"docs":{"0":{"ref":0,"tf":0.012195121951219513},"1":{"ref":1,"tf":0.012345679012345678}}}}}}},"y":{"docs":{},"s":{"docs":{},"t":{"docs":{},"e":{"docs":{},"m":{"docs":{"0":{"ref":0,"tf":0.024390243902439025},"1":{"ref":1,"tf":0.024691358024691357}}}}}},"n":{"docs":{},"t":{"docs":{},"a":{"docs":{},"x":{"docs":{"3":{"ref":3,"tf":0.027777777777777776},"4":{"ref":4,"tf":0.027777777777777776}}}}}}},"i":{"docs":{},"m":{"docs":{},"p":{"docs":{},"l":{"docs":{"1":{"ref":1,"tf":0.05555555555555555},"2":{"ref":2,"tf":0.05555555555555555},"3":{"ref":3,"tf":0.006944444444444444},"4":{"ref":4,"tf":0.006944444444444444},"5":{"ref":5,"tf":3.351515151515151}}}},"i":{"docs":{},"l":{"docs":{},"a":{"docs":{},"r":{"docs":{"3":{"ref":3,"tf":0.006944444444444444},"4":{"ref":4,"tf":0.006944444444444444}}}}}}},"t":{"docs":{},"e":{"docs":{},".":{"docs":{},"p":{"docs":{},"o":{"docs":{},"s":{"docs":{},"t":{"docs":{"2":{"ref":2,"tf":0.038461538461538464}}}}}}}}}},"m":{"docs":{},"a":{"docs":{},"l":{"docs":{},"l":{"docs":{},">":{"docs":{},"{":{"docs":{},"{":{"docs":{},"/":{"docs":{},"d":{"docs":{},"a":{"docs":{},"t":{"docs":{"2":{"ref":2,"tf":0.0625}}}}}}}}}}}}},"p":{"docs":{},"a":{"docs":{},"n":{"docs":{"2":{"ref":2,"tf":0.14285714285714285},"3":{"ref":3,"tf":0.14285714285714285}}}},"e":{"docs":{},"c":{"docs":{},"i":{"docs":{},"a":{"docs":{},"l":{"docs":{"3":{"ref":3,"tf":0.006944444444444444},"4":{"ref":4,"tf":0.006944444444444444}}}},"f":{"docs":{"3":{"ref":3,"tf":0.006944444444444444},"4":{"ref":4,"tf":0.006944444444444444}},"i":{"docs":{"3":{"ref":3,"tf":0.006944444444444444},"4":{"ref":4,"tf":0.006944444444444444}}}}}}}},"h":{"docs":{},"a":{"docs":{},"d":{"docs":{},"e":{"docs":{"4":{"ref":4,"tf":0.01818181818181818},"5":{"ref":5,"tf":0.01818181818181818}}},"o":{"docs":{},"w":{"docs":{"4":{"ref":4,"tf":0.03636363636363636},"5":{"ref":5,"tf":0.03636363636363636}}}}}}},"o":{"docs":{},"f":{"docs":{},"t":{"docs":{"4":{"ref":4,"tf":0.01818181818181818},"5":{"ref":5,"tf":0.01818181818181818}}}}}},"t":{"docs":{},"e":{"docs":{},"x":{"docs":{},"a":{"docs":{"0":{"ref":0,"tf":0.012195121951219513},"1":{"ref":1,"tf":0.012345679012345678}}}}},"h":{"docs":{},"e":{"docs":{},"o":{"docs":{},"r":{"docs":{},"i":{"docs":{"0":{"ref":0,"tf":0.024390243902439025},"1":{"ref":1,"tf":0.024691358024691357}}}}}},"a":{"docs":{},"n":{"docs":{},"k":{"docs":{"3":{"ref":3,"tf":0.006944444444444444},"4":{"ref":4,"tf":0.006944444444444444}}}}},"i":{"docs":{},"n":{"docs":{},"g":{"docs":{"3":{"ref":3,"tf":0.006944444444444444},"4":{"ref":4,"tf":0.006944444444444444}}}}}},"u":{"docs":{},"r":{"docs":{},"e":{"docs":{"0":{"ref":0,"tf":0.012195121951219513},"1":{"ref":1,"tf":0.012345679012345678}}}}},"r":{"docs":{},"a":{"docs":{},"c":{"docs":{},"e":{"docs":{"4":{"ref":4,"tf":0.05454545454545454},"5":{"ref":5,"tf":0.05454545454545454}},"r":{"docs":{"1":{"ref":1,"tf":0.05555555555555555},"2":{"ref":2,"tf":0.05555555555555555},"4":{"ref":4,"tf":3.351515151515151},"5":{"ref":5,"tf":3.351515151515151}}}}}},"i":{"docs":{},"g":{"docs":{},"g":{"docs":{},"e":{"docs":{},"r":{"docs":{"3":{"ref":3,"tf":0.020833333333333332},"4":{"ref":4,"tf":0.020833333333333332}}}}}},"a":{"docs":{},"n":{"docs":{},"g":{"docs":{},"l":{"docs":{},"e":{"docs":{},"/":{"docs":{},"f":{"docs":{},"a":{"docs":{},"c":{"docs":{"4":{"ref":4,"tf":0.01818181818181818},"5":{"ref":5,"tf":0.01818181818181818}}}}}}}}}}}}},"a":{"docs":{},"k":{"docs":{},"e":{"docs":{"3":{"ref":3,"tf":0.006944444444444444},"4":{"ref":4,"tf":0.006944444444444444}}}}},"y":{"docs":{},"p":{"docs":{},"e":{"docs":{"3":{"ref":3,"tf":0.006944444444444444},"4":{"ref":4,"tf":0.006944444444444444}}}}},"i":{"docs":{},"t":{"docs":{},"l":{"docs":{"2":{"ref":2,"tf":0.07142857142857142},"3":{"ref":3,"tf":0.07142857142857142}}}}}},"u":{"docs":{},"n":{"docs":{},"i":{"docs":{},"v":{"docs":{},"e":{"docs":{},"r":{"docs":{},"s":{"docs":{"0":{"ref":0,"tf":0.012195121951219513},"1":{"ref":1,"tf":0.012345679012345678}}}}}}},"d":{"docs":{},"e":{"docs":{},"r":{"docs":{"3":{"ref":3,"tf":0.006944444444444444},"4":{"ref":4,"tf":0.006944444444444444}}}}}},"s":{"docs":{"1":{"ref":1,"tf":0.05555555555555555},"2":{"ref":2,"tf":0.05555555555555555},"3":{"ref":3,"tf":1.6944444444444442},"4":{"ref":4,"tf":1.6944444444444442}},"e":{"docs":{},"r":{"docs":{},"-":{"docs":{},"d":{"docs":{},"e":{"docs":{},"f":{"docs":{},"i":{"docs":{},"n":{"docs":{"3":{"ref":3,"tf":0.006944444444444444},"4":{"ref":4,"tf":0.006944444444444444}}}}}}}}}}},"l":{"docs":{"2":{"ref":2,"tf":0.045454545454545456}}},"r":{"docs":{},"l":{"docs":{"2":{"ref":2,"tf":0.07142857142857142},"3":{"ref":3,"tf":0.07142857142857142}}}}},"d":{"docs":{},"e":{"docs":{},"c":{"docs":{"1":{"ref":1,"tf":0.05555555555555555},"2":{"ref":2,"tf":0.05555555555555555}}},"f":{"docs":{},"a":{"docs":{},"u":{"docs":{},"l":{"docs":{},"t":{"docs":{"3":{"ref":3,"tf":0.006944444444444444},"4":{"ref":4,"tf":0.006944444444444444}}}}}},"i":{"docs":{},"n":{"docs":{"3":{"ref":3,"tf":0.020833333333333332},"4":{"ref":4,"tf":0.020833333333333332}}}}},"s":{"docs":{},"i":{"docs":{},"g":{"docs":{},"n":{"docs":{"3":{"ref":3,"tf":0.020833333333333332},"4":{"ref":4,"tf":0.020833333333333332}}}}}},"t":{"docs":{},"a":{"docs":{},"i":{"docs":{},"l":{"docs":{"3":{"ref":3,"tf":0.006944444444444444},"4":{"ref":4,"tf":0.006944444444444444}}}}}},"v":{"docs":{},"e":{"docs":{},"l":{"docs":{},"o":{"docs":{},"p":{"docs":{"3":{"ref":3,"tf":0.006944444444444444},"4":{"ref":4,"tf":0.006944444444444444}}}}}}},"p":{"docs":{},"t":{"docs":{},"h":{"docs":{"4":{"ref":4,"tf":0.01818181818181818},"5":{"ref":5,"tf":0.01818181818181818}}}}}},"s":{"docs":{},"l":{"docs":{"1":{"ref":1,"tf":0.1111111111111111},"2":{"ref":2,"tf":0.1111111111111111},"3":{"ref":3,"tf":1.6874999999999998},"4":{"ref":4,"tf":1.6874999999999998}}}},"a":{"docs":{},"t":{"docs":{},"e":{"docs":{"2":{"ref":2,"tf":0.03125}},"t":{"docs":{},"i":{"docs":{},"m":{"docs":{},"e":{"docs":{},"=":{"docs":{},"\"":{"docs":{},"{":{"docs":{},"{":{"docs":{},"p":{"docs":{},"u":{"docs":{},"b":{"docs":{},"d":{"docs":{"2":{"ref":2,"tf":0.0625}}}}}}}}}}}}}},"}":{"docs":{},"}":{"docs":{},"<":{"docs":{},"s":{"docs":{},"m":{"docs":{},"a":{"docs":{},"l":{"docs":{},"l":{"docs":{},">":{"docs":{},"<":{"docs":{},"t":{"docs":{},"i":{"docs":{},"m":{"docs":{"2":{"ref":2,"tf":0.0625}}}}}}}}}}}}}}}}}},"i":{"docs":{},"s":{"docs":{},"t":{"docs":{},"r":{"docs":{},"i":{"docs":{},"b":{"docs":{},"u":{"docs":{},"t":{"docs":{"4":{"ref":4,"tf":0.01818181818181818},"5":{"ref":5,"tf":0.01818181818181818}}}}}}}}},"v":{"docs":{"2":{"ref":2,"tf":0.05263157894736842}}}}},"r":{"docs":{},"a":{"docs":{},"i":{"docs":{"1":{"ref":1,"tf":0.05555555555555555},"2":{"ref":2,"tf":0.05555555555555555},"4":{"ref":4,"tf":3.424242424242424},"5":{"ref":5,"tf":3.424242424242424}}}},"e":{"docs":{},"s":{"docs":{},"u":{"docs":{},"l":{"docs":{},"t":{"docs":{"2":{"ref":2,"tf":5.071428571428571},"3":{"ref":3,"tf":5.071428571428571}}}}}},"f":{"docs":{},"l":{"docs":{},"e":{"docs":{},"c":{"docs":{},"t":{"docs":{"4":{"ref":4,"tf":0.03636363636363636},"5":{"ref":5,"tf":0.03636363636363636}}}}}},"r":{"docs":{},"a":{"docs":{},"c":{"docs":{},"t":{"docs":{"4":{"ref":4,"tf":0.03636363636363636},"5":{"ref":5,"tf":0.03636363636363636}}}}}}},"n":{"docs":{},"d":{"docs":{},"e":{"docs":{},"r":{"docs":{"4":{"ref":4,"tf":0.03636363636363636},"5":{"ref":5,"tf":0.03636363636363636}}}}}}}},"n":{"docs":{},"a":{"docs":{},"m":{"docs":{},"e":{"docs":{"3":{"ref":3,"tf":0.013888888888888888},"4":{"ref":4,"tf":0.013888888888888888}}}}},"e":{"docs":{},"w":{"docs":{"3":{"ref":3,"tf":0.027777777777777776},"4":{"ref":4,"tf":0.027777777777777776}}}},"o":{"docs":{},"r":{"docs":{},"m":{"docs":{},"a":{"docs":{},"l":{"docs":{"4":{"ref":4,"tf":0.03636363636363636},"5":{"ref":5,"tf":0.03636363636363636}}}}}}}},"j":{"docs":{},"i":{"docs":{},"t":{"docs":{},"t":{"docs":{},"e":{"docs":{},"r":{"docs":{"4":{"ref":4,"tf":0.01818181818181818},"5":{"ref":5,"tf":0.01818181818181818}}}}}}}},"k":{"docs":{},"d":{"docs":{},"-":{"docs":{},"t":{"docs":{},"r":{"docs":{},"e":{"docs":{},"e":{"docs":{"4":{"ref":4,"tf":0.01818181818181818},"5":{"ref":5,"tf":0.01818181818181818}}}}}}}}},"y":{"docs":{"2":{"ref":2,"tf":0.03125}}}},"length":36308},"corpusTokens":["2014","2015","2016","3.92","4","4.00","5","action","adatp","advantag","algebra","algorithm","allow","antialias","antialis","architectur","argument","arrai","articl","artif","artifact","attenu","attribut","austin","b","b.","basic","c","calculu","call","class=\"rel","class=\"ty-post-timestamp","class=\"ty-post-titl","comput","condit","consist","contain","cooper","core","cours","creat","cs312)introduct","cs313k)logic","cs314)data","cs331h)introduct","cs343h)introduct","cs345h)program","cs347)oper","cs349)contemporari","cs384g","cs384g)introduct","cs429h)comput","cs439h)oper","date","datetime=\"{{pubd","date}}<small><tim","dec","default","defin","depth","design","detail","develop","distribut","div","dsl","e","educ","element","endfor","entiti","entri","equat","exampl","facilit","featur","field","follow","foo","function","functions/discret","fundament","game","gamel","github","glossi","gpa","graduat","graphic","group","h3","homepag","honor","href","href=\"{{url}}\">{{title}}</a","idea","implement","inherit","instanc","integr","intellig","intend","interpol","intersect","introduct","issu","jitter","kd-tree","languag","li","m341)linear","m358k)appli","m358k)number","m408c)differenti","m408d)sequenc","m427k)differenti","m427l)vector","mansi","manual","map","mar","mark","math","mathemat","matrix","multithread","multivari","name","new","normal","object","on","oop","optim","organ","overrid","paramet","phong","player","polymesh","post","post.url","program","progress","project","propos","prototype/class","pubdat","pubdate>{{displaydate}}</tim","punch","rai","reflect","refract","render","result","scala","scene","scholar","scienc","script","search","seri","set","shade","shadow","similar","simpl","site.post","small>{{/dat","soft","span","special","specif","specifi","statist","structur","summer","syntax","system","take","texa","thank","theori","thing","titl","trace","tracer","triangle/fac","trigger","ture","type","ul","under","univers","url","us","user-defin","y"],"pipeline":["stopWordFilter","stemmer"]}}